eiprice/__init__.py
eiprice/httpclient/__init__.py
eiprice/httpclient/adapters/__init__.py
eiprice/httpclient/adapters/asynchronous.py
eiprice/httpclient/adapters/specs/__init__.py
eiprice/httpclient/adapters/specs/http.py
eiprice/httpclient/adapters/strategy/__init__.py
eiprice/httpclient/adapters/strategy/driver.py
eiprice/httpclient/commands/__init__.py
eiprice/httpclient/commands/action.py
eiprice/httpclient/commands/download.py
eiprice/httpclient/core/__init__.py
eiprice/httpclient/core/asynchronous.py
eiprice/httpclient/core/base.py
eiprice/httpclient/core/chrome.py
eiprice/httpclient/core/methods.py
eiprice/httpclient/core/synchronous.py
eiprice-2.0.12.dist-info/METADATA
eiprice-2.0.12.dist-info/WHEEL
eiprice-2.0.12.dist-info/top_level.txt
eiprice-2.0.12.dist-info/RECORD
